authorizenot/__init__.py
authorizenot/apicontractsv1.py
authorizenot/apicontrollers.py
authorizenot/apicontrollersbase.py
authorizenot/constants.py
authorizenot/utility.py
AuthorizeNot-1.1.4.8.dist-info/LICENSE.txt
AuthorizeNot-1.1.4.8.dist-info/METADATA
AuthorizeNot-1.1.4.8.dist-info/WHEEL
AuthorizeNot-1.1.4.8.dist-info/top_level.txt
AuthorizeNot-1.1.4.8.dist-info/RECORD
